{"app_entry": {}, "conda_platforms": ["noarch"], "full_name": "bioconda/badread", "owner": {"description": "Bioconda is a distribution of bioinformatics software realized as a channel for the versatile Conda package manager.", "url": "", "company": "", "user_type": "org", "location": "", "login": "bioconda", "created_at": "2015-09-11 22:59:20.880000+00:00", "name": "bioconda"}, "home": "https://github.com/rrwick/Badread", "source_git_url": null, "source_git_tag": null, "app_type": {}, "upvoted": 0, "id": "5f60c4c6a58f0d0a15c4879a", "app_summary": {}, "public": true, "revision": 4, "files": [{"description": null, "basename": "noarch/badread-0.1.5-py_0.tar.bz2", "labels": ["main"], "dependencies": {"depends": [{"name": "edlib", "specs": []}, {"name": "matplotlib-base", "specs": []}, {"name": "numpy", "specs": []}, {"name": "pip", "specs": []}, {"name": "python", "specs": [[">=", "3.6"]]}, {"name": "scipy", "specs": []}]}, "distribution_type": "conda", "attrs": {"build_number": 0, "license": "GNU General Public License v3 (GPLv3)", "has_prefix": false, "license_family": "GPL3", "noarch": "python", "machine": null, "platform": null, "depends": ["edlib", "matplotlib-base", "numpy", "pip", "python >=3.6", "scipy"], "build": "py_0", "timestamp": 1600173755743, "arch": null, "operatingsystem": null, "target-triplet": "None-any-None", "subdir": "noarch"}, "full_name": "bioconda/badread/0.1.5/noarch/badread-0.1.5-py_0.tar.bz2", "owner": "bioconda", "size": 6163162, "upload_time": "2020-09-15 13:42:31.176000+00:00", "ndownloads": 296, "download_url": "//api.anaconda.org/download/bioconda/badread/0.1.5/noarch/badread-0.1.5-py_0.tar.bz2", "version": "0.1.5", "md5": "d550d0ea125afaa43b1aa430a814bae2", "type": "conda"}, {"description": null, "basename": "noarch/badread-0.2.0-py_0.tar.bz2", "labels": ["main"], "dependencies": {"depends": [{"name": "edlib", "specs": []}, {"name": "matplotlib-base", "specs": []}, {"name": "numpy", "specs": []}, {"name": "pip", "specs": []}, {"name": "python", "specs": [[">=", "3.6"]]}, {"name": "scipy", "specs": []}]}, "distribution_type": "conda", "attrs": {"build_number": 0, "license": "GNU General Public License v3 (GPLv3)", "has_prefix": false, "license_family": "GPL3", "noarch": "python", "machine": null, "platform": null, "depends": ["edlib", "matplotlib-base", "numpy", "pip", "python >=3.6", "scipy"], "build": "py_0", "timestamp": 1612999378546, "arch": null, "operatingsystem": null, "target-triplet": "None-any-None", "subdir": "noarch"}, "full_name": "bioconda/badread/0.2.0/noarch/badread-0.2.0-py_0.tar.bz2", "owner": "bioconda", "size": 9627789, "upload_time": "2021-02-19 20:30:33.355000+00:00", "ndownloads": 203, "download_url": "//api.anaconda.org/download/bioconda/badread/0.2.0/noarch/badread-0.2.0-py_0.tar.bz2", "version": "0.2.0", "md5": "ba4b7deaccec9045a481796eb7edb485", "type": "conda"}], "package_types": ["conda"], "description": "", "releases": [{"version": "0.1.5", "distributions": [], "full_name": "bioconda/badread/0.1.5"}, {"version": "0.2.0", "distributions": [], "full_name": "bioconda/badread/0.2.0"}], "html_url": "http://anaconda.org/bioconda/badread", "builds": ["py_0"], "watchers": 1, "dev_url": null, "name": "badread", "license": "GNU General Public License v3 (GPLv3)", "versions": ["0.1.5", "0.2.0"], "url": "http://api.anaconda.org/packages/bioconda/badread", "created_at": "2020-09-15 13:42:30.104000+00:00", "modified_at": "2021-02-19 20:30:33.933000+00:00", "latest_version": "0.2.0", "summary": "A long read simulator that can imitate many types of read problems", "license_url": null, "doc_url": null}